missense/__init__.py
missense/missense.py
pymissense-1.1.0.dist-info/LICENSE
pymissense-1.1.0.dist-info/METADATA
pymissense-1.1.0.dist-info/WHEEL
pymissense-1.1.0.dist-info/entry_points.txt
pymissense-1.1.0.dist-info/top_level.txt
pymissense-1.1.0.dist-info/RECORD
