Metadata-Version: 2.1
Name: pymissense
Version: 1.1.0
Summary: PyMissense create the plot and modified pdb as shown in the AlphaMissense Paper
Author-email: Thorsten Wagner <thorsten.wagner@mpi-dortmund.mpg.de>, Tobias Raisch <tobias.raisch@mpi-dortmund.mpg.de>
License-File: LICENSE
Requires-Dist: matplotlib
Requires-Dist: numpy
Requires-Dist: requests
